{
"components":["CR","TI"],
"phases":["BCC_A2","LAVES_C15"],
"conditions":{
"P":101325,
"T":[1103.15,1093.15,1023.15,1048.15,1018.15,1013.15,1008.15,1008.15,
	1003.15,963.15,938.15,933.15]
},
"broadcast_conditions":false,
"output":"ZPF",
"values":[
[["BCC_A2", ["TI", "CR"], [0.974, 0.026]], ["LAVES_C15", ["TI", "CR"],[null, null]]],
[["BCC_A2", ["TI", "CR"], [0.976, 0.024]], ["LAVES_C15", ["TI", "CR"], [null,null]]],
[["BCC_A2", ["TI", "CR"], [0.952, 0.048]], ["LAVES_C15", ["TI", "CR"], [null,null]]],
[["BCC_A2", ["TI", "CR"], [0.959, 0.041]], ["LAVES_C15", ["TI", "CR"], [null,null]]],
[["BCC_A2", ["TI", "CR"], [0.934, 0.066]], ["LAVES_C15", ["TI", "CR"], [null,null]]],
[["BCC_A2", ["TI", "CR"], [0.924, 0.076]], ["LAVES_C15", ["TI", "CR"], [null,null]]],
[["BCC_A2", ["TI", "CR"], [0.929, 0.071]], ["LAVES_C15", ["TI", "CR"], [null,null]]],
[["BCC_A2", ["TI", "CR"], [0.921, 0.079]], ["LAVES_C15", ["TI", "CR"], [null,null]]],
[["BCC_A2", ["TI", "CR"], [0.920, 0.080]], ["LAVES_C15", ["TI", "CR"], [null,null]]],
[["BCC_A2", ["TI", "CR"], [0.909, 0.091]], ["LAVES_C15", ["TI", "CR"], [null,null]]],
[["BCC_A2", ["TI", "CR"], [0.896, 0.104]], ["LAVES_C15", ["TI", "CR"], [null,null]]],
[["BCC_A2", ["TI", "CR"], [0.884, 0.116]], ["LAVES_C15", ["TI", "CR"], [null,null]]]
],
"reference":"mcquillan1954redetermination",
"comment":"converted all to atomic percent"
}